{
    "row_num" : "",
    "id" : "30331796",
    "trans_no" : "6668650707966769603011",
    "date" : "2022-10-27T17:04:30Z",
    "merchant_id" : "TESTONEPAY",
    "acquirer" : "4",
    "trans_ref" : "REF_1666865070078",
    "trans_type" : "VOID_REFUND",
    "amount" : {
      "total" : "1000.00",
      "currency" : "VND",
      "refund_total" : "0.00"
    },
    "currency" : "VND",
    "response" : "0",
    "order_ref" : "Ma Don Hang",
    "card_number" : "400000****0002",
    "name_on_card" : "",
    "auth_code" : "831000",
    "payment_auth_id" : "",
    "batch_number" : " ",
    "tranaction_id" : "30331794",
    "card_type" : "Visa",
    "base_status" : "CONFIRM_VOID_REFUND",
    "risk_assesment" : "",
    "bank_id" : "Citibank",
    "advance_status" : "",
    "installment_status" : "",
    "installment_bank" : "",
    "customer_mobile" : "",
    "customer_email" : "",
    "epp" : "",
    "fraud_check" : "",
    "customer_name" : ""
  }