{
  "row_num" : "",
  "id" : "30331790",
  "trans_no" : "6668650593406737603007",
  "date" : "2022-10-27T17:04:18Z",
  "merchant_id" : "TESTONEPAY",
  "acquirer" : "4",
  "trans_ref" : "REF_1666865058561",
  "trans_type" : "VOID_PURCHASE",
  "amount" : {
    "total" : "10000.00",
    "currency" : "VND",
    "refund_total" : "0.00"
  },
  "currency" : "VND",
  "response" : "0",
  "order_ref" : "Ma Don Hang",
  "card_number" : "400000****0002",
  "name_on_card" : "",
  "auth_code" : "831000",
  "payment_auth_id" : "",
  "batch_number" : " ",
  "tranaction_id" : "30331789",
  "card_type" : "Visa",
  "base_status" : "CONFIRM_VOID_PURCHASE",
  "risk_assesment" : "",
  "bank_id" : "Citibank",
  "advance_status" : "",
  "installment_status" : "",
  "installment_bank" : "",
  "customer_mobile" : "",
  "customer_email" : "",
  "epp" : "",
  "fraud_check" : "",
  "customer_name" : ""
}